LICENSE
MANIFEST.in
README.md
setup.cfg
setup.py
baton/__init__.py
baton/admin.py
baton/apps.py
baton/config.py
baton/models.py
baton/tests.py
baton/urls.py
baton/views.py
baton/autodiscover/__init__.py
baton/autodiscover/admin.py
baton/locale/it/LC_MESSAGES/django.mo
baton/locale/it/LC_MESSAGES/django.po
baton/static/admin/css/base.css
baton/static/admin/css/changelists.css
baton/static/admin/css/dashboard.css
baton/static/admin/css/forms.css
baton/static/admin/css/responsive.css
baton/static/baton/app/.babelrc
baton/static/baton/app/.eslintignore
baton/static/baton/app/.eslintrc
baton/static/baton/app/.tern-project
baton/static/baton/app/package-lock.json
baton/static/baton/app/package.json
baton/static/baton/app/postcss.config.js
baton/static/baton/app/webpack.config.babel.js
baton/static/baton/app/dist/baton.min.js
baton/static/baton/app/dist/baton.min.js.map
baton/static/baton/app/dist/fa-brands-400.eot
baton/static/baton/app/dist/fa-brands-400.svg
baton/static/baton/app/dist/fa-brands-400.ttf
baton/static/baton/app/dist/fa-solid-900.eot
baton/static/baton/app/dist/fa-solid-900.svg
baton/static/baton/app/dist/fa-solid-900.ttf
baton/static/baton/app/dist/fontawesome-webfont.eot
baton/static/baton/app/dist/fontawesome-webfont.svg
baton/static/baton/app/dist/fontawesome-webfont.ttf
baton/static/baton/app/src/.vimrc
baton/static/baton/app/src/index.js
baton/static/baton/app/src/core/ActionResult.js
baton/static/baton/app/src/core/Analytics.js
baton/static/baton/app/src/core/ChangeForm.js
baton/static/baton/app/src/core/ChangeList.js
baton/static/baton/app/src/core/Filer.js
baton/static/baton/app/src/core/Footer.js
baton/static/baton/app/src/core/Menu.js
baton/static/baton/app/src/core/Navbar.js
baton/static/baton/app/src/core/PasswordChange.js
baton/static/baton/app/src/core/Tabs.js
baton/static/baton/app/src/core/Utils.js
baton/static/baton/app/src/core/i18n.js
baton/static/baton/app/src/fonts/Dosis-Bold.ttf
baton/static/baton/app/src/fonts/Dosis-ExtraBold.ttf
django_baton_v2.egg-info/PKG-INFO
django_baton_v2.egg-info/SOURCES.txt
django_baton_v2.egg-info/dependency_links.txt
django_baton_v2.egg-info/requires.txt
django_baton_v2.egg-info/top_level.txt